gabriel_protocol/__init__.py
gabriel_protocol/gabriel_pb2.py
gabriel_protocol-4.0.dist-info/licenses/LICENSE
gabriel_protocol-4.0.dist-info/METADATA
gabriel_protocol-4.0.dist-info/WHEEL
gabriel_protocol-4.0.dist-info/top_level.txt
gabriel_protocol-4.0.dist-info/RECORD
